complextorch/__init__.py
complextorch/_cvrandom.py
complextorch/_cvtensor.py
complextorch/nn/__init__.py
complextorch/nn/functional.py
complextorch/nn/modules/__init__.py
complextorch/nn/modules/batchnorm.py
complextorch/nn/modules/conv.py
complextorch/nn/modules/dropout.py
complextorch/nn/modules/fft.py
complextorch/nn/modules/layernorm.py
complextorch/nn/modules/linear.py
complextorch/nn/modules/loss.py
complextorch/nn/modules/manifold.py
complextorch/nn/modules/mask.py
complextorch/nn/modules/pooling.py
complextorch/nn/modules/softmax.py
complextorch/nn/modules/activation/__init__.py
complextorch/nn/modules/activation/complex_relu.py
complextorch/nn/modules/activation/fully_complex.py
complextorch/nn/modules/activation/split_type_A.py
complextorch/nn/modules/activation/split_type_B.py
complextorch/nn/modules/attention/__init__.py
complextorch/nn/modules/attention/eca.py
complextorch/nn/modules/attention/mca.py
complextorch-1.2.0.dist-info/licenses/LICENSE
complextorch-1.2.0.dist-info/METADATA
complextorch-1.2.0.dist-info/WHEEL
complextorch-1.2.0.dist-info/top_level.txt
complextorch-1.2.0.dist-info/RECORD
