Metadata-Version: 2.4
Name: complextorch
Version: 1.2.0
Summary: A lightweight complex-valued neural network package built on PyTorch
Home-page: https://www.github.com/josiahwsmith10/complextorch
Author: Josiah W. Smith
Author-email: josiah.radar@gmail.com
Project-URL: Bug Tracker, https://github.com/josiahwsmith10/complextorch/issues
Project-URL: Documentation, https://complextorch.readthedocs.io/en/latest/index.html
Project-URL: GitHub, https://github.com/josiahwsmith10/complextorch
Classifier: Programming Language :: Python :: 3
Classifier: License :: OSI Approved :: GNU General Public License v3 or later (GPLv3+)
Classifier: Operating System :: OS Independent
Requires-Python: >=3.6
License-File: LICENSE
Requires-Dist: numpy>=2.2.0
Requires-Dist: setuptools>=68.2.2
Requires-Dist: torch>=1.11.0
Requires-Dist: deprecated>=1.2.18
Dynamic: author
Dynamic: author-email
Dynamic: classifier
Dynamic: description
Dynamic: description-content-type
Dynamic: home-page
Dynamic: license-file
Dynamic: project-url
Dynamic: requires-dist
Dynamic: requires-python
Dynamic: summary
